_quickjs.so
quickjs/__init__.py
py2quickjs-0.5.0.dist-info/LICENSE
py2quickjs-0.5.0.dist-info/METADATA
py2quickjs-0.5.0.dist-info/WHEEL
py2quickjs-0.5.0.dist-info/top_level.txt
py2quickjs-0.5.0.dist-info/RECORD
