Metadata-Version: 2.1
Name: py2quickjs
Version: 0.5.0
Summary: Wrapping the quickjs C library.
Home-page: https://github.com/un44444444/py2quickjs
Author: Petter Strandmark
Author-email: petter.strandmark@gmail.com
Maintainer: Stone C
Maintainer-email: un44444444@gmail.com
License: UNKNOWN
Platform: UNKNOWN
Requires-Python: >=2.7, <3
